uitext/__init__.py
uitext/ascii/__init__.py
uitext/ascii/gridformatter.py
uitext/ascii/html2ascii.py
uitext/ascii/xlsx2ascii.py
uitext/selenium/__init__.py
uitext/selenium/selenium_utils.py
uitext/sikuli/__init__.py
uitext/sikuli/sikuli_utils.py
uitext/sikuli/sikuli_wrapper.py
uitext-1.4.0.dist-info/LICENSE
uitext-1.4.0.dist-info/METADATA
uitext-1.4.0.dist-info/WHEEL
uitext-1.4.0.dist-info/entry_points.txt
uitext-1.4.0.dist-info/top_level.txt
uitext-1.4.0.dist-info/RECORD
