Metadata-Version: 2.1
Name: uitext
Version: 1.4.0
Summary: UI-related utilities for approval testing for Selenium and Sikuli
Author-email: Geoff Bache <geoff.bache@pobox.com>
License: GNU LESSER GENERAL PUBLIC LICENSE
Project-URL: Homepage, https://github.com/texttest/uitext
Project-URL: Bug Tracker, https://github.com/texttest/uitext/issues
Classifier: Programming Language :: Python :: 3
Classifier: License :: OSI Approved :: GNU Lesser General Public License v3 or later (LGPLv3+)
Classifier: Operating System :: OS Independent
Requires-Python: >=3.7
License-File: LICENSE
